technic_solder_client-2.0.dist-info/METADATA
technic_solder_client-2.0.dist-info/RECORD
technic_solder_client-2.0.dist-info/DESCRIPTION.rst
technic_solder_client-2.0.dist-info/top_level.txt
technic_solder_client-2.0.dist-info/WHEEL
technic_solder_client-2.0.dist-info/metadata.json
technic_solder_client-2.0.data/scripts/solder
technic_solder_client-2.0.data/scripts/solder.py
technic/__init__.py
technic/solder/exceptions.py
technic/solder/client.py
technic/solder/__init__.py
technic/solder/app.py
technic/solder/cli/__init__.py
technic/solder/cli/command.py
technic/solder/cli/app.py
technic/solder/cli/commands/server.py
technic/solder/cli/commands/modpacks.py
technic/solder/cli/commands/__init__.py
technic/solder/cli/commands/builds.py
technic/solder/cli/commands/mods.py
tests/test_modpack.py
tests/test_mod.py
tests/__init__.py
tests/test_builds.py
tests/utils.py
