Metadata-Version: 2.0
Name: technic-solder-client
Version: 2.0
Summary: Python implementation of a Technic Solder client
Home-page: https://github.com/cadyyan/technic-solder-client
Author: Cadyyan
Author-email: cadyyan@gmail.com
License: MIT
Platform: UNKNOWN
Requires-Dist: colorama
Requires-Dist: mock
Requires-Dist: nose
Requires-Dist: requests
Requires-Dist: tabulate
Requires-Dist: urllib3
Requires-Dist: urwid
